MANIFEST.in
README.md
setup.py
tbas/BusyIndicator.qml
tbas/__init__.py
tbas/cli.py
tbas/gui.py
tbas/icon.png
tbas/mainwindow.py
tbas/mainwindow.ui
tbas/tbas.py
tbas/test_tbas.py
tbas.egg-info/PKG-INFO
tbas.egg-info/SOURCES.txt
tbas.egg-info/dependency_links.txt
tbas.egg-info/entry_points.txt
tbas.egg-info/not-zip-safe
tbas.egg-info/requires.txt
tbas.egg-info/top_level.txt