Metadata-Version: 1.1
Name: tbas
Version: 0.1
Summary: Tis But A Scratch
Home-page: https://github.com/cniemira/tbas
Author: CJ Niemira
Author-email: siege@siege.org
License: UNKNOWN
Keywords: tbas
Platform: UNKNOWN
Classifier: Development Status :: 3 - Alpha
Classifier: License :: Public Domain
Classifier: Programming Language :: Other
Classifier: Programming Language :: Python
Classifier: Topic :: Text Editors :: Integrated Development Environments (IDE)
